Metadata-Version: 1.1
Name: pwdpp
Version: 1.0.6
Summary: Portable pwd (print working directory).
Home-page: https://bitbucket.org/hhsprings/pwdpp
Author: Hiroaki Itoh
Author-email: xwhhsprings@gmail.com
License: BSD 3-Clause License
Keywords: pwd,portable,windows,cygwin,msys,msys2
Platform: UNKNOWN
Classifier: Intended Audience :: End Users/Desktop
Classifier: License :: OSI Approved :: BSD License
Classifier: Environment :: Console
Classifier: Topic :: Utilities
Classifier: Programming Language :: Python :: 2
Classifier: Programming Language :: Python :: 2.7
Classifier: Programming Language :: Python :: 3
Classifier: Programming Language :: Python :: 3.4
Classifier: Programming Language :: Python :: 3.5
Classifier: Programming Language :: Python :: 3.6
